cardanomsg/__init__.py
cardanomsg/transaction.py
cardanomsg/wallet.py
cardanomsg-0.1.5.dist-info/licenses/LICENSE
cardanomsg-0.1.5.dist-info/METADATA
cardanomsg-0.1.5.dist-info/WHEEL
cardanomsg-0.1.5.dist-info/top_level.txt
cardanomsg-0.1.5.dist-info/RECORD
