Metadata-Version: 2.4
Name: cardanomsg
Version: 0.1.5
Summary: A module to send Cardano ADA with a message in the metadata.
Home-page: https://github.com/primaryobjects/cardanomsg
Author: Kory Becker
Project-URL: Homepage, https://github.com/primaryobjects/cardanomsg
Project-URL: Issues, https://github.com/primaryobjects/cardanomsg/issues
Classifier: Programming Language :: Python :: 3
Classifier: License :: OSI Approved :: MIT License
Classifier: Operating System :: OS Independent
Requires-Python: >=3.6
License-File: LICENSE
Requires-Dist: blockfrost-python
Requires-Dist: pycardano
Dynamic: home-page
Dynamic: license-file
Dynamic: requires-python
